{
  "docs": {
    "Web":["web-installation","web-authentication","web-conversation", "web-conversation-assignment","actionable-messages","web-customization","web-localization","web-logout","web-troubleshooting"],
    "Android": ["android-installation","android-authentication","android-conversation","android-pushnotification","android-customization","android-localization", "android-logout"],
    "iOS":["ios-installation","ios-authentication","ios-conversation","ios-pushnotification","ios-customization","ios-localization","ios-logout"],
    "Ionic/Cordova/Phonegap":["cordova-installation","cordova-authentication","cordova-conversation","cordova-pushnotification","cordova-customization", "cordova-logout","cordova-resolving-errors"],
    "Platform APIs":["api-authentication","api-detail"],
    "Bots" : ["bot-setup","bot-dialogflow-integration","bot-custom-integration","bot-samples"],
    "Configuration":["email-fallback-configuration","webhooks-configuration","access-token-url-configuration"]
  },
  "docs-other": {
    "First Category": ["doc4", "doc5"]
  }
}

